meerkat/__init__.py
meerkat/api.py
meerkat/cli.py
meerkat/ping_sounds/default_ping.wav
meerkatio-1.21.dist-info/LICENSE
meerkatio-1.21.dist-info/METADATA
meerkatio-1.21.dist-info/WHEEL
meerkatio-1.21.dist-info/entry_points.txt
meerkatio-1.21.dist-info/top_level.txt
meerkatio-1.21.dist-info/RECORD
