Metadata-Version: 2.1
Name: meerkatio
Version: 1.21
Summary: Personal push notification and debug tool for multi-tasking software developers
Home-page: https://meerkatio.com
Author: MeerkatIO
License: GNU GENERAL PUBLIC LICENSE
Keywords: notification,push-notification,alerting,personal,productivity,Slack,CLI,System Tray,Ping,Email,SMS,data science,jupyter,notebook
License-File: LICENSE
Requires-Dist: requests
Requires-Dist: click
Requires-Dist: typing-extensions (==4.11.0)
Requires-Dist: ipython
Requires-Dist: pygame
Requires-Dist: plyer
